[
    {
        "publicId": "80000000-0000-0000-0000-00000000e003",
        "host": {
            "pseudo": "Me",
            "publicId": "10000000-0000-0000-0000-000000000001",
            "isGuest": true,
            "isBot": false,
            "slug": "me",
            "createdAt": "2024-01-24T16:33:29.586Z"
        },
        "hostedGameToPlayers": [
            {
                "player": {
                    "pseudo": "Me",
                    "publicId": "10000000-0000-0000-0000-000000000001",
                    "isGuest": true,
                    "isBot": false,
                    "slug": "me",
                    "createdAt": "2024-01-24T16:33:29.586Z"
                }
            },
            {
                "player": {
                    "pseudo": "TestBot",
                    "publicId": "80000000-0000-0000-0000-000000000008",
                    "isGuest": false,
                    "isBot": true,
                    "slug": "testbot",
                    "createdAt": "2024-01-24T16:33:29.586Z"
                }
            }
        ],
        "timeControl": {
            "state": "running",
            "currentPlayer": 0,
            "players": [
                { "totalRemainingTime": 600000 },
                { "totalRemainingTime": 600000 }
            ]
        },
        "boardsize": 11,
        "firstPlayer": null,
        "swapRule": true,
        "opponentType": "ai",
        "opponentPublicId": null,
        "timeControlType": {
            "family": "fischer",
            "options": {
                "initialTime": 600000,
                "timeIncrement": 5000,
                "maxTime": 600000
            }
        },
        "chatMessages": [],
        "state": "playing",
        "createdAt": "2024-01-25T10:00:00.000Z",
        "moves": [],
        "moveTimestamps": [],
        "currentPlayerIndex": 0,
        "winner": null,
        "outcome": null,
        "startedAt": "2024-01-25T10:00:05.000Z",
        "lastMoveAt": "2024-01-25T10:00:05.000Z",
        "endedAt": null
    },
    {
        "publicId": "30000000-0000-0000-0000-00000000bbbb",
        "host": {
            "pseudo": "Challenger",
            "publicId": "30000000-0000-0000-0000-000000000003",
            "isGuest": false,
            "isBot": false,
            "slug": "challenger",
            "createdAt": "2024-01-24T16:33:29.586Z"
        },
        "hostedGameToPlayers": [
            {
                "player": {
                    "pseudo": "Challenger",
                    "publicId": "30000000-0000-0000-0000-000000000003",
                    "isGuest": false,
                    "isBot": false,
                    "slug": "challenger",
                    "createdAt": "2024-01-24T16:33:29.586Z"
                }
            }
        ],
        "timeControl": {
            "state": "ready",
            "currentPlayer": 0,
            "players": [
                { "totalRemainingTime": 600000 },
                { "totalRemainingTime": 600000 }
            ]
        },
        "boardsize": 11,
        "firstPlayer": null,
        "swapRule": true,
        "opponentType": "player",
        "opponentPublicId": "10000000-0000-0000-0000-000000000001",
        "timeControlType": {
            "family": "fischer",
            "options": {
                "initialTime": 600000,
                "timeIncrement": 5000,
                "maxTime": 600000
            }
        },
        "chatMessages": [],
        "state": "created",
        "createdAt": "2024-01-25T10:00:00.000Z",
        "moves": [],
        "moveTimestamps": [],
        "currentPlayerIndex": 0,
        "winner": null,
        "outcome": null,
        "startedAt": null,
        "lastMoveAt": null,
        "endedAt": null
    },
    {
        "publicId": "70000000-0000-0000-0000-00000000e001",
        "host": {
            "pseudo": "Rival",
            "publicId": "70000000-0000-0000-0000-000000000007",
            "isGuest": false,
            "isBot": false,
            "slug": "rival",
            "createdAt": "2024-01-24T16:33:29.586Z"
        },
        "hostedGameToPlayers": [
            {
                "player": {
                    "pseudo": "Rival",
                    "publicId": "70000000-0000-0000-0000-000000000007",
                    "isGuest": false,
                    "isBot": false,
                    "slug": "rival",
                    "createdAt": "2024-01-24T16:33:29.586Z"
                }
            },
            {
                "player": {
                    "pseudo": "Me",
                    "publicId": "10000000-0000-0000-0000-000000000001",
                    "isGuest": true,
                    "isBot": false,
                    "slug": "me",
                    "createdAt": "2024-01-24T16:33:29.586Z"
                }
            }
        ],
        "timeControl": {
            "state": "running",
            "currentPlayer": 1,
            "players": [
                { "totalRemainingTime": 600000 },
                { "totalRemainingTime": 600000 }
            ]
        },
        "boardsize": 11,
        "firstPlayer": null,
        "swapRule": true,
        "opponentType": "player",
        "opponentPublicId": null,
        "timeControlType": {
            "family": "fischer",
            "options": {
                "initialTime": 600000,
                "timeIncrement": 5000,
                "maxTime": 600000
            }
        },
        "chatMessages": [],
        "state": "playing",
        "createdAt": "2024-01-25T10:00:00.000Z",
        "moves": [],
        "moveTimestamps": [],
        "currentPlayerIndex": 1,
        "winner": null,
        "outcome": null,
        "startedAt": "2024-01-25T10:00:05.000Z",
        "lastMoveAt": "2024-01-25T10:00:05.000Z",
        "endedAt": null
    }
]
